HISTORY.rst
LICENSE
MANIFEST.in
README.rst
setup.py
clans/__init__.py
clans/__main__.py
clans/fmt.py
clans/scraper.py
clans/ui.py
clans/util.py
clans.egg-info/PKG-INFO
clans.egg-info/SOURCES.txt
clans.egg-info/dependency_links.txt
clans.egg-info/entry_points.txt
clans.egg-info/requires.txt
clans.egg-info/top_level.txt
clans/ext/__init__.py
clans/ext/backup.py
clans/ext/example.py
clans/ext/newlove.py